README.md
setup.cfg
setup.py
ppi_client/__init__.py
ppi_client/ppi.py
ppi_client/ppi_api_client.py
ppi_client/ppi_exceptions.py
ppi_client/ppi_restclient.py
ppi_client.egg-info/PKG-INFO
ppi_client.egg-info/SOURCES.txt
ppi_client.egg-info/dependency_links.txt
ppi_client.egg-info/requires.txt
ppi_client.egg-info/top_level.txt
ppi_client/api/__init__.py
ppi_client/api/accounts.py
ppi_client/api/configuration.py
ppi_client/api/constants.py
ppi_client/api/marketdata.py
ppi_client/api/orders.py
ppi_client/api/realtime.py
ppi_client/models/__init__.py
ppi_client/models/account_movements.py
ppi_client/models/bank_account_request.py
ppi_client/models/cancel_bank_account_request.py
ppi_client/models/disclaimer.py
ppi_client/models/estimate_bonds.py
ppi_client/models/foreign_bank_account_request.py
ppi_client/models/foreign_bank_account_request_dto.py
ppi_client/models/instrument.py
ppi_client/models/investing_profile.py
ppi_client/models/investing_profile_answer.py
ppi_client/models/order.py
ppi_client/models/order_budget.py
ppi_client/models/order_confirm.py
ppi_client/models/transfer_budget.py