Metadata-Version: 2.1
Name: ppi-client
Version: 1.2.1
Summary: Portfolio Personal Inversiones API
Home-page: UNKNOWN
Author: PPI SDK <api@portfoliopersonal.com>
Author-email: api@portfoliopersonal.com
License: UNKNOWN
Keywords: SDK,Portfolio Personal Inversiones API
Platform: UNKNOWN
